airdot/__init__.py
airdot/cli.py
airdot/deployer.py
airdot/version.py
airdot/collection/__init__.py
airdot/collection/collections.py
airdot/contants/__init__.py
airdot/contants/runtime_images.py
airdot/data_models/__init__.py
airdot/data_models/deployment.py
airdot/data_models/kserve_model.py
airdot/data_models/seldon_model.py
airdot/helpers/__init__.py
airdot/helpers/authentication.py
airdot/helpers/content_helper.py
airdot/helpers/data_object_helpers.py
airdot/helpers/docker_helper.py
airdot/helpers/gcs_helper.py
airdot/helpers/general_helpers.py
airdot/helpers/kubernetes_helper.py
airdot/helpers/minio_helper.py
airdot/helpers/network_helper.py
airdot/helpers/pkg_helpers.py
airdot/helpers/redis_helper.py
airdot/helpers/runtime_helper.py
airdot/helpers/s2i_helper.py
airdot/helpers/seldon_helper.py
airdot/helpers/template_helpers.py
airdot/helpers/version_helpers.py
tests/__init__.py
tests/deployer_test.py
tests/test_files/__init__.py
tests/test_files/example_1.py
airdot-0.6.0b0.dist-info/LICENSE
airdot-0.6.0b0.dist-info/METADATA
airdot-0.6.0b0.dist-info/WHEEL
airdot-0.6.0b0.dist-info/top_level.txt
airdot-0.6.0b0.dist-info/RECORD
