Metadata-Version: 2.1
Name: airdot
Version: 0.6.0b0
Summary: A code base for deploying ml api 
Home-page: https://github.com/airdot-io/airdot-Deploy/
Author: airdot-io
Author-email: airdot-io <abhinav199530singh@gmail.com>
License: MIT License
Project-URL: Homepage, https://github.com/airdot-io/airdot-Deploy
Classifier: License :: OSI Approved :: MIT License
Classifier: Programming Language :: Python
Classifier: Programming Language :: Python :: 3.8
Requires-Python: >=3.7.0
License-File: LICENSE
Requires-Dist: google-api-python-client ==2.78
Requires-Dist: google-cloud-core ==2.3
Requires-Dist: google-cloud-storage ==2.7
Requires-Dist: google-auth
Requires-Dist: boto ==2.49
Requires-Dist: botocore ==1.29
Requires-Dist: boto3 ==1.26
Requires-Dist: docker ==6.1
Requires-Dist: redis ==4.5
Requires-Dist: pydantic ==1.10.8
Requires-Dist: kubernetes
Requires-Dist: tabulate
Provides-Extra: dev
Requires-Dist: black ==22.6.0 ; extra == 'dev'
Requires-Dist: pytest ==7.1.2 ; extra == 'dev'
Requires-Dist: google-api-python-client ==2.78.0 ; extra == 'dev'
Requires-Dist: google-cloud-core ==2.3.2 ; extra == 'dev'
Requires-Dist: google-cloud-storage ==2.7.0 ; extra == 'dev'
Requires-Dist: google-auth ; extra == 'dev'
Requires-Dist: zstd ==1.5.2.6 ; extra == 'dev'
Requires-Dist: boto ==2.49.0 ; extra == 'dev'
Requires-Dist: botocore ==1.29.127 ; extra == 'dev'
Requires-Dist: boto3 ==1.26 ; extra == 'dev'
Requires-Dist: docker ==6.1.2 ; extra == 'dev'
Requires-Dist: redis ==4.5.5 ; extra == 'dev'
Requires-Dist: pydantic ==1.10.8 ; extra == 'dev'
Requires-Dist: kubernetes ==26 ; extra == 'dev'
